	<OLifE>
		<ApplicationEntryClientSearchData>
			<MirStartSub></MirStartSub>
			<MirDvCliSrchQty></MirDvCliSrchQty>
			<MirSimultAppInd></MirSimultAppInd>
			<MirCliIdG>
				<MirCliIdT></MirCliIdT>
				<MirCliIdT></MirCliIdT>
				<MirCliIdT></MirCliIdT>
				<MirCliIdT></MirCliIdT>
				<MirCliIdT></MirCliIdT>
				<MirCliIdT></MirCliIdT>
				<MirCliIdT></MirCliIdT>
				<MirCliIdT></MirCliIdT>
				<MirCliIdT></MirCliIdT>
				<MirCliIdT></MirCliIdT>
				<MirCliIdT></MirCliIdT>
				<MirCliIdT></MirCliIdT>
				<MirCliIdT></MirCliIdT>
				<MirCliIdT></MirCliIdT>
				<MirCliIdT></MirCliIdT>
				<MirCliIdT></MirCliIdT>
				<MirCliIdT></MirCliIdT>
				<MirCliIdT></MirCliIdT>
				<MirCliIdT></MirCliIdT>
				<MirCliIdT></MirCliIdT>
			</MirCliIdG>
			<MirEntrGivNmG>
				<MirEntrGivNmT></MirEntrGivNmT>
				<MirEntrGivNmT></MirEntrGivNmT>
				<MirEntrGivNmT></MirEntrGivNmT>
				<MirEntrGivNmT></MirEntrGivNmT>
				<MirEntrGivNmT></MirEntrGivNmT>
				<MirEntrGivNmT></MirEntrGivNmT>
				<MirEntrGivNmT></MirEntrGivNmT>
				<MirEntrGivNmT></MirEntrGivNmT>
				<MirEntrGivNmT></MirEntrGivNmT>
				<MirEntrGivNmT></MirEntrGivNmT>
				<MirEntrGivNmT></MirEntrGivNmT>
				<MirEntrGivNmT></MirEntrGivNmT>
				<MirEntrGivNmT></MirEntrGivNmT>
				<MirEntrGivNmT></MirEntrGivNmT>
				<MirEntrGivNmT></MirEntrGivNmT>
				<MirEntrGivNmT></MirEntrGivNmT>
				<MirEntrGivNmT></MirEntrGivNmT>
				<MirEntrGivNmT></MirEntrGivNmT>
				<MirEntrGivNmT></MirEntrGivNmT>
				<MirEntrGivNmT></MirEntrGivNmT>
			</MirEntrGivNmG>
			<MirEntrSurNmG>
				<MirEntrSurNmT></MirEntrSurNmT>
				<MirEntrSurNmT></MirEntrSurNmT>
				<MirEntrSurNmT></MirEntrSurNmT>
				<MirEntrSurNmT></MirEntrSurNmT>
				<MirEntrSurNmT></MirEntrSurNmT>
				<MirEntrSurNmT></MirEntrSurNmT>
				<MirEntrSurNmT></MirEntrSurNmT>
				<MirEntrSurNmT></MirEntrSurNmT>
				<MirEntrSurNmT></MirEntrSurNmT>
				<MirEntrSurNmT></MirEntrSurNmT>
				<MirEntrSurNmT></MirEntrSurNmT>
				<MirEntrSurNmT></MirEntrSurNmT>
				<MirEntrSurNmT></MirEntrSurNmT>
				<MirEntrSurNmT></MirEntrSurNmT>
				<MirEntrSurNmT></MirEntrSurNmT>
				<MirEntrSurNmT></MirEntrSurNmT>
				<MirEntrSurNmT></MirEntrSurNmT>
				<MirEntrSurNmT></MirEntrSurNmT>
				<MirEntrSurNmT></MirEntrSurNmT>
				<MirEntrSurNmT></MirEntrSurNmT>
			</MirEntrSurNmG>
			<MirEntrMidNmG>
				<MirEntrMidNmT></MirEntrMidNmT>
				<MirEntrMidNmT></MirEntrMidNmT>
				<MirEntrMidNmT></MirEntrMidNmT>
				<MirEntrMidNmT></MirEntrMidNmT>
				<MirEntrMidNmT></MirEntrMidNmT>
				<MirEntrMidNmT></MirEntrMidNmT>
				<MirEntrMidNmT></MirEntrMidNmT>
				<MirEntrMidNmT></MirEntrMidNmT>
				<MirEntrMidNmT></MirEntrMidNmT>
				<MirEntrMidNmT></MirEntrMidNmT>
				<MirEntrMidNmT></MirEntrMidNmT>
				<MirEntrMidNmT></MirEntrMidNmT>
				<MirEntrMidNmT></MirEntrMidNmT>
				<MirEntrMidNmT></MirEntrMidNmT>
				<MirEntrMidNmT></MirEntrMidNmT>
				<MirEntrMidNmT></MirEntrMidNmT>
				<MirEntrMidNmT></MirEntrMidNmT>
				<MirEntrMidNmT></MirEntrMidNmT>
				<MirEntrMidNmT></MirEntrMidNmT>
				<MirEntrMidNmT></MirEntrMidNmT>
			</MirEntrMidNmG>
			<MirCliCoEntrNmG>
				<MirCliCoEntrNmT></MirCliCoEntrNmT>
				<MirCliCoEntrNmT></MirCliCoEntrNmT>
				<MirCliCoEntrNmT></MirCliCoEntrNmT>
				<MirCliCoEntrNmT></MirCliCoEntrNmT>
				<MirCliCoEntrNmT></MirCliCoEntrNmT>
				<MirCliCoEntrNmT></MirCliCoEntrNmT>
				<MirCliCoEntrNmT></MirCliCoEntrNmT>
				<MirCliCoEntrNmT></MirCliCoEntrNmT>
				<MirCliCoEntrNmT></MirCliCoEntrNmT>
				<MirCliCoEntrNmT></MirCliCoEntrNmT>
				<MirCliCoEntrNmT></MirCliCoEntrNmT>
				<MirCliCoEntrNmT></MirCliCoEntrNmT>
				<MirCliCoEntrNmT></MirCliCoEntrNmT>
				<MirCliCoEntrNmT></MirCliCoEntrNmT>
				<MirCliCoEntrNmT></MirCliCoEntrNmT>
				<MirCliCoEntrNmT></MirCliCoEntrNmT>
				<MirCliCoEntrNmT></MirCliCoEntrNmT>
				<MirCliCoEntrNmT></MirCliCoEntrNmT>
				<MirCliCoEntrNmT></MirCliCoEntrNmT>
				<MirCliCoEntrNmT></MirCliCoEntrNmT>
			</MirCliCoEntrNmG>
			<MirCliBthDtG>
				<MirCliBthDtT></MirCliBthDtT>
				<MirCliBthDtT></MirCliBthDtT>
				<MirCliBthDtT></MirCliBthDtT>
				<MirCliBthDtT></MirCliBthDtT>
				<MirCliBthDtT></MirCliBthDtT>
				<MirCliBthDtT></MirCliBthDtT>
				<MirCliBthDtT></MirCliBthDtT>
				<MirCliBthDtT></MirCliBthDtT>
				<MirCliBthDtT></MirCliBthDtT>
				<MirCliBthDtT></MirCliBthDtT>
				<MirCliBthDtT></MirCliBthDtT>
				<MirCliBthDtT></MirCliBthDtT>
				<MirCliBthDtT></MirCliBthDtT>
				<MirCliBthDtT></MirCliBthDtT>
				<MirCliBthDtT></MirCliBthDtT>
				<MirCliBthDtT></MirCliBthDtT>
				<MirCliBthDtT></MirCliBthDtT>
				<MirCliBthDtT></MirCliBthDtT>
				<MirCliBthDtT></MirCliBthDtT>
				<MirCliBthDtT></MirCliBthDtT>
			</MirCliBthDtG>
			<MirCliSexCdG>
				<MirCliSexCdT></MirCliSexCdT>
				<MirCliSexCdT></MirCliSexCdT>
				<MirCliSexCdT></MirCliSexCdT>
				<MirCliSexCdT></MirCliSexCdT>
				<MirCliSexCdT></MirCliSexCdT>
				<MirCliSexCdT></MirCliSexCdT>
				<MirCliSexCdT></MirCliSexCdT>
				<MirCliSexCdT></MirCliSexCdT>
				<MirCliSexCdT></MirCliSexCdT>
				<MirCliSexCdT></MirCliSexCdT>
				<MirCliSexCdT></MirCliSexCdT>
				<MirCliSexCdT></MirCliSexCdT>
				<MirCliSexCdT></MirCliSexCdT>
				<MirCliSexCdT></MirCliSexCdT>
				<MirCliSexCdT></MirCliSexCdT>
				<MirCliSexCdT></MirCliSexCdT>
				<MirCliSexCdT></MirCliSexCdT>
				<MirCliSexCdT></MirCliSexCdT>
				<MirCliSexCdT></MirCliSexCdT>
				<MirCliSexCdT></MirCliSexCdT>
			</MirCliSexCdG>
			<MirCliAddrLn1TxtG>
				<MirCliAddrLn1TxtT></MirCliAddrLn1TxtT>
				<MirCliAddrLn1TxtT></MirCliAddrLn1TxtT>
				<MirCliAddrLn1TxtT></MirCliAddrLn1TxtT>
				<MirCliAddrLn1TxtT></MirCliAddrLn1TxtT>
				<MirCliAddrLn1TxtT></MirCliAddrLn1TxtT>
				<MirCliAddrLn1TxtT></MirCliAddrLn1TxtT>
				<MirCliAddrLn1TxtT></MirCliAddrLn1TxtT>
				<MirCliAddrLn1TxtT></MirCliAddrLn1TxtT>
				<MirCliAddrLn1TxtT></MirCliAddrLn1TxtT>
				<MirCliAddrLn1TxtT></MirCliAddrLn1TxtT>
				<MirCliAddrLn1TxtT></MirCliAddrLn1TxtT>
				<MirCliAddrLn1TxtT></MirCliAddrLn1TxtT>
				<MirCliAddrLn1TxtT></MirCliAddrLn1TxtT>
				<MirCliAddrLn1TxtT></MirCliAddrLn1TxtT>
				<MirCliAddrLn1TxtT></MirCliAddrLn1TxtT>
				<MirCliAddrLn1TxtT></MirCliAddrLn1TxtT>
				<MirCliAddrLn1TxtT></MirCliAddrLn1TxtT>
				<MirCliAddrLn1TxtT></MirCliAddrLn1TxtT>
				<MirCliAddrLn1TxtT></MirCliAddrLn1TxtT>
				<MirCliAddrLn1TxtT></MirCliAddrLn1TxtT>
			</MirCliAddrLn1TxtG>
			<MirCliAddrLn2TxtG>
				<MirCliAddrLn2TxtT></MirCliAddrLn2TxtT>
				<MirCliAddrLn2TxtT></MirCliAddrLn2TxtT>
				<MirCliAddrLn2TxtT></MirCliAddrLn2TxtT>
				<MirCliAddrLn2TxtT></MirCliAddrLn2TxtT>
				<MirCliAddrLn2TxtT></MirCliAddrLn2TxtT>
				<MirCliAddrLn2TxtT></MirCliAddrLn2TxtT>
				<MirCliAddrLn2TxtT></MirCliAddrLn2TxtT>
				<MirCliAddrLn2TxtT></MirCliAddrLn2TxtT>
				<MirCliAddrLn2TxtT></MirCliAddrLn2TxtT>
				<MirCliAddrLn2TxtT></MirCliAddrLn2TxtT>
				<MirCliAddrLn2TxtT></MirCliAddrLn2TxtT>
				<MirCliAddrLn2TxtT></MirCliAddrLn2TxtT>
				<MirCliAddrLn2TxtT></MirCliAddrLn2TxtT>
				<MirCliAddrLn2TxtT></MirCliAddrLn2TxtT>
				<MirCliAddrLn2TxtT></MirCliAddrLn2TxtT>
				<MirCliAddrLn2TxtT></MirCliAddrLn2TxtT>
				<MirCliAddrLn2TxtT></MirCliAddrLn2TxtT>
				<MirCliAddrLn2TxtT></MirCliAddrLn2TxtT>
				<MirCliAddrLn2TxtT></MirCliAddrLn2TxtT>
				<MirCliAddrLn2TxtT></MirCliAddrLn2TxtT>
			</MirCliAddrLn2TxtG>
			<MirCliAddrLn3TxtG>
				<MirCliAddrLn3TxtT></MirCliAddrLn3TxtT>
				<MirCliAddrLn3TxtT></MirCliAddrLn3TxtT>
				<MirCliAddrLn3TxtT></MirCliAddrLn3TxtT>
				<MirCliAddrLn3TxtT></MirCliAddrLn3TxtT>
				<MirCliAddrLn3TxtT></MirCliAddrLn3TxtT>
				<MirCliAddrLn3TxtT></MirCliAddrLn3TxtT>
				<MirCliAddrLn3TxtT></MirCliAddrLn3TxtT>
				<MirCliAddrLn3TxtT></MirCliAddrLn3TxtT>
				<MirCliAddrLn3TxtT></MirCliAddrLn3TxtT>
				<MirCliAddrLn3TxtT></MirCliAddrLn3TxtT>
				<MirCliAddrLn3TxtT></MirCliAddrLn3TxtT>
				<MirCliAddrLn3TxtT></MirCliAddrLn3TxtT>
				<MirCliAddrLn3TxtT></MirCliAddrLn3TxtT>
				<MirCliAddrLn3TxtT></MirCliAddrLn3TxtT>
				<MirCliAddrLn3TxtT></MirCliAddrLn3TxtT>
				<MirCliAddrLn3TxtT></MirCliAddrLn3TxtT>
				<MirCliAddrLn3TxtT></MirCliAddrLn3TxtT>
				<MirCliAddrLn3TxtT></MirCliAddrLn3TxtT>
				<MirCliAddrLn3TxtT></MirCliAddrLn3TxtT>
				<MirCliAddrLn3TxtT></MirCliAddrLn3TxtT>
			</MirCliAddrLn3TxtG>
			<MirCliCityNmTxtG>
				<MirCliCityNmTxtT></MirCliCityNmTxtT>
				<MirCliCityNmTxtT></MirCliCityNmTxtT>
				<MirCliCityNmTxtT></MirCliCityNmTxtT>
				<MirCliCityNmTxtT></MirCliCityNmTxtT>
				<MirCliCityNmTxtT></MirCliCityNmTxtT>
				<MirCliCityNmTxtT></MirCliCityNmTxtT>
				<MirCliCityNmTxtT></MirCliCityNmTxtT>
				<MirCliCityNmTxtT></MirCliCityNmTxtT>
				<MirCliCityNmTxtT></MirCliCityNmTxtT>
				<MirCliCityNmTxtT></MirCliCityNmTxtT>
				<MirCliCityNmTxtT></MirCliCityNmTxtT>
				<MirCliCityNmTxtT></MirCliCityNmTxtT>
				<MirCliCityNmTxtT></MirCliCityNmTxtT>
				<MirCliCityNmTxtT></MirCliCityNmTxtT>
				<MirCliCityNmTxtT></MirCliCityNmTxtT>
				<MirCliCityNmTxtT></MirCliCityNmTxtT>
				<MirCliCityNmTxtT></MirCliCityNmTxtT>
				<MirCliCityNmTxtT></MirCliCityNmTxtT>
				<MirCliCityNmTxtT></MirCliCityNmTxtT>
				<MirCliCityNmTxtT></MirCliCityNmTxtT>
			</MirCliCityNmTxtG>
			<MirCliCtryCdG>
				<MirCliCtryCdT></MirCliCtryCdT>
				<MirCliCtryCdT></MirCliCtryCdT>
				<MirCliCtryCdT></MirCliCtryCdT>
				<MirCliCtryCdT></MirCliCtryCdT>
				<MirCliCtryCdT></MirCliCtryCdT>
				<MirCliCtryCdT></MirCliCtryCdT>
				<MirCliCtryCdT></MirCliCtryCdT>
				<MirCliCtryCdT></MirCliCtryCdT>
				<MirCliCtryCdT></MirCliCtryCdT>
				<MirCliCtryCdT></MirCliCtryCdT>
				<MirCliCtryCdT></MirCliCtryCdT>
				<MirCliCtryCdT></MirCliCtryCdT>
				<MirCliCtryCdT></MirCliCtryCdT>
				<MirCliCtryCdT></MirCliCtryCdT>
				<MirCliCtryCdT></MirCliCtryCdT>
				<MirCliCtryCdT></MirCliCtryCdT>
				<MirCliCtryCdT></MirCliCtryCdT>
				<MirCliCtryCdT></MirCliCtryCdT>
				<MirCliCtryCdT></MirCliCtryCdT>
				<MirCliCtryCdT></MirCliCtryCdT>
			</MirCliCtryCdG>
			<MirCliPstlCdG>
				<MirCliPstlCdT></MirCliPstlCdT>
				<MirCliPstlCdT></MirCliPstlCdT>
				<MirCliPstlCdT></MirCliPstlCdT>
				<MirCliPstlCdT></MirCliPstlCdT>
				<MirCliPstlCdT></MirCliPstlCdT>
				<MirCliPstlCdT></MirCliPstlCdT>
				<MirCliPstlCdT></MirCliPstlCdT>
				<MirCliPstlCdT></MirCliPstlCdT>
				<MirCliPstlCdT></MirCliPstlCdT>
				<MirCliPstlCdT></MirCliPstlCdT>
				<MirCliPstlCdT></MirCliPstlCdT>
				<MirCliPstlCdT></MirCliPstlCdT>
				<MirCliPstlCdT></MirCliPstlCdT>
				<MirCliPstlCdT></MirCliPstlCdT>
				<MirCliPstlCdT></MirCliPstlCdT>
				<MirCliPstlCdT></MirCliPstlCdT>
				<MirCliPstlCdT></MirCliPstlCdT>
				<MirCliPstlCdT></MirCliPstlCdT>
				<MirCliPstlCdT></MirCliPstlCdT>
				<MirCliPstlCdT></MirCliPstlCdT>
			</MirCliPstlCdG>
			<MirCliCrntLocCdG>
				<MirCliCrntLocCdT></MirCliCrntLocCdT>
				<MirCliCrntLocCdT></MirCliCrntLocCdT>
				<MirCliCrntLocCdT></MirCliCrntLocCdT>
				<MirCliCrntLocCdT></MirCliCrntLocCdT>
				<MirCliCrntLocCdT></MirCliCrntLocCdT>
				<MirCliCrntLocCdT></MirCliCrntLocCdT>
				<MirCliCrntLocCdT></MirCliCrntLocCdT>
				<MirCliCrntLocCdT></MirCliCrntLocCdT>
				<MirCliCrntLocCdT></MirCliCrntLocCdT>
				<MirCliCrntLocCdT></MirCliCrntLocCdT>
				<MirCliCrntLocCdT></MirCliCrntLocCdT>
				<MirCliCrntLocCdT></MirCliCrntLocCdT>
				<MirCliCrntLocCdT></MirCliCrntLocCdT>
				<MirCliCrntLocCdT></MirCliCrntLocCdT>
				<MirCliCrntLocCdT></MirCliCrntLocCdT>
				<MirCliCrntLocCdT></MirCliCrntLocCdT>
				<MirCliCrntLocCdT></MirCliCrntLocCdT>
				<MirCliCrntLocCdT></MirCliCrntLocCdT>
				<MirCliCrntLocCdT></MirCliCrntLocCdT>
				<MirCliCrntLocCdT></MirCliCrntLocCdT>
			</MirCliCrntLocCdG>
			<MirPolIdG>
				<MirPolIdT></MirPolIdT>
				<MirPolIdT></MirPolIdT>
				<MirPolIdT></MirPolIdT>
				<MirPolIdT></MirPolIdT>
				<MirPolIdT></MirPolIdT>
				<MirPolIdT></MirPolIdT>
				<MirPolIdT></MirPolIdT>
				<MirPolIdT></MirPolIdT>
				<MirPolIdT></MirPolIdT>
				<MirPolIdT></MirPolIdT>
				<MirPolIdT></MirPolIdT>
				<MirPolIdT></MirPolIdT>
				<MirPolIdT></MirPolIdT>
				<MirPolIdT></MirPolIdT>
				<MirPolIdT></MirPolIdT>
				<MirPolIdT></MirPolIdT>
				<MirPolIdT></MirPolIdT>
				<MirPolIdT></MirPolIdT>
				<MirPolIdT></MirPolIdT>
				<MirPolIdT></MirPolIdT>
			</MirPolIdG>
			<MirCliSrchMtchCdG>
				<MirCliSrchMtchCdT></MirCliSrchMtchCdT>
				<MirCliSrchMtchCdT></MirCliSrchMtchCdT>
				<MirCliSrchMtchCdT></MirCliSrchMtchCdT>
				<MirCliSrchMtchCdT></MirCliSrchMtchCdT>
				<MirCliSrchMtchCdT></MirCliSrchMtchCdT>
				<MirCliSrchMtchCdT></MirCliSrchMtchCdT>
				<MirCliSrchMtchCdT></MirCliSrchMtchCdT>
				<MirCliSrchMtchCdT></MirCliSrchMtchCdT>
				<MirCliSrchMtchCdT></MirCliSrchMtchCdT>
				<MirCliSrchMtchCdT></MirCliSrchMtchCdT>
				<MirCliSrchMtchCdT></MirCliSrchMtchCdT>
				<MirCliSrchMtchCdT></MirCliSrchMtchCdT>
				<MirCliSrchMtchCdT></MirCliSrchMtchCdT>
				<MirCliSrchMtchCdT></MirCliSrchMtchCdT>
				<MirCliSrchMtchCdT></MirCliSrchMtchCdT>
				<MirCliSrchMtchCdT></MirCliSrchMtchCdT>
				<MirCliSrchMtchCdT></MirCliSrchMtchCdT>
				<MirCliSrchMtchCdT></MirCliSrchMtchCdT>
				<MirCliSrchMtchCdT></MirCliSrchMtchCdT>
				<MirCliSrchMtchCdT></MirCliSrchMtchCdT>
			</MirCliSrchMtchCdG>
			<MirCliBthLocCdG>
				<MirCliBthLocCdT></MirCliBthLocCdT>
				<MirCliBthLocCdT></MirCliBthLocCdT>
				<MirCliBthLocCdT></MirCliBthLocCdT>
				<MirCliBthLocCdT></MirCliBthLocCdT>
				<MirCliBthLocCdT></MirCliBthLocCdT>
				<MirCliBthLocCdT></MirCliBthLocCdT>
				<MirCliBthLocCdT></MirCliBthLocCdT>
				<MirCliBthLocCdT></MirCliBthLocCdT>
				<MirCliBthLocCdT></MirCliBthLocCdT>
				<MirCliBthLocCdT></MirCliBthLocCdT>
				<MirCliBthLocCdT></MirCliBthLocCdT>
				<MirCliBthLocCdT></MirCliBthLocCdT>
				<MirCliBthLocCdT></MirCliBthLocCdT>
				<MirCliBthLocCdT></MirCliBthLocCdT>
				<MirCliBthLocCdT></MirCliBthLocCdT>
				<MirCliBthLocCdT></MirCliBthLocCdT>
				<MirCliBthLocCdT></MirCliBthLocCdT>
				<MirCliBthLocCdT></MirCliBthLocCdT>
				<MirCliBthLocCdT></MirCliBthLocCdT>
				<MirCliBthLocCdT></MirCliBthLocCdT>
			</MirCliBthLocCdG>
			<MirCliMaritStatCdG>
				<MirCliMaritStatCdT></MirCliMaritStatCdT>
				<MirCliMaritStatCdT></MirCliMaritStatCdT>
				<MirCliMaritStatCdT></MirCliMaritStatCdT>
				<MirCliMaritStatCdT></MirCliMaritStatCdT>
				<MirCliMaritStatCdT></MirCliMaritStatCdT>
				<MirCliMaritStatCdT></MirCliMaritStatCdT>
				<MirCliMaritStatCdT></MirCliMaritStatCdT>
				<MirCliMaritStatCdT></MirCliMaritStatCdT>
				<MirCliMaritStatCdT></MirCliMaritStatCdT>
				<MirCliMaritStatCdT></MirCliMaritStatCdT>
				<MirCliMaritStatCdT></MirCliMaritStatCdT>
				<MirCliMaritStatCdT></MirCliMaritStatCdT>
				<MirCliMaritStatCdT></MirCliMaritStatCdT>
				<MirCliMaritStatCdT></MirCliMaritStatCdT>
				<MirCliMaritStatCdT></MirCliMaritStatCdT>
				<MirCliMaritStatCdT></MirCliMaritStatCdT>
				<MirCliMaritStatCdT></MirCliMaritStatCdT>
				<MirCliMaritStatCdT></MirCliMaritStatCdT>
				<MirCliMaritStatCdT></MirCliMaritStatCdT>
				<MirCliMaritStatCdT></MirCliMaritStatCdT>
			</MirCliMaritStatCdG>
			<MirCliOtherFirstNmG>
				<MirCliOtherFirstNmT></MirCliOtherFirstNmT>
				<MirCliOtherFirstNmT></MirCliOtherFirstNmT>
				<MirCliOtherFirstNmT></MirCliOtherFirstNmT>
				<MirCliOtherFirstNmT></MirCliOtherFirstNmT>
				<MirCliOtherFirstNmT></MirCliOtherFirstNmT>
				<MirCliOtherFirstNmT></MirCliOtherFirstNmT>
				<MirCliOtherFirstNmT></MirCliOtherFirstNmT>
				<MirCliOtherFirstNmT></MirCliOtherFirstNmT>
				<MirCliOtherFirstNmT></MirCliOtherFirstNmT>
				<MirCliOtherFirstNmT></MirCliOtherFirstNmT>
				<MirCliOtherFirstNmT></MirCliOtherFirstNmT>
				<MirCliOtherFirstNmT></MirCliOtherFirstNmT>
				<MirCliOtherFirstNmT></MirCliOtherFirstNmT>
				<MirCliOtherFirstNmT></MirCliOtherFirstNmT>
				<MirCliOtherFirstNmT></MirCliOtherFirstNmT>
				<MirCliOtherFirstNmT></MirCliOtherFirstNmT>
				<MirCliOtherFirstNmT></MirCliOtherFirstNmT>
				<MirCliOtherFirstNmT></MirCliOtherFirstNmT>
				<MirCliOtherFirstNmT></MirCliOtherFirstNmT>
				<MirCliOtherFirstNmT></MirCliOtherFirstNmT>
			</MirCliOtherFirstNmG>
			<MirCliOtherMidNmG>
				<MirCliOtherMidNmT></MirCliOtherMidNmT>
				<MirCliOtherMidNmT></MirCliOtherMidNmT>
				<MirCliOtherMidNmT></MirCliOtherMidNmT>
				<MirCliOtherMidNmT></MirCliOtherMidNmT>
				<MirCliOtherMidNmT></MirCliOtherMidNmT>
				<MirCliOtherMidNmT></MirCliOtherMidNmT>
				<MirCliOtherMidNmT></MirCliOtherMidNmT>
				<MirCliOtherMidNmT></MirCliOtherMidNmT>
				<MirCliOtherMidNmT></MirCliOtherMidNmT>
				<MirCliOtherMidNmT></MirCliOtherMidNmT>
				<MirCliOtherMidNmT></MirCliOtherMidNmT>
				<MirCliOtherMidNmT></MirCliOtherMidNmT>
				<MirCliOtherMidNmT></MirCliOtherMidNmT>
				<MirCliOtherMidNmT></MirCliOtherMidNmT>
				<MirCliOtherMidNmT></MirCliOtherMidNmT>
				<MirCliOtherMidNmT></MirCliOtherMidNmT>
				<MirCliOtherMidNmT></MirCliOtherMidNmT>
				<MirCliOtherMidNmT></MirCliOtherMidNmT>
				<MirCliOtherMidNmT></MirCliOtherMidNmT>
				<MirCliOtherMidNmT></MirCliOtherMidNmT>
			</MirCliOtherMidNmG>
			<MirCliOtherLastNmG>
				<MirCliOtherLastNmT></MirCliOtherLastNmT>
				<MirCliOtherLastNmT></MirCliOtherLastNmT>
				<MirCliOtherLastNmT></MirCliOtherLastNmT>
				<MirCliOtherLastNmT></MirCliOtherLastNmT>
				<MirCliOtherLastNmT></MirCliOtherLastNmT>
				<MirCliOtherLastNmT></MirCliOtherLastNmT>
				<MirCliOtherLastNmT></MirCliOtherLastNmT>
				<MirCliOtherLastNmT></MirCliOtherLastNmT>
				<MirCliOtherLastNmT></MirCliOtherLastNmT>
				<MirCliOtherLastNmT></MirCliOtherLastNmT>
				<MirCliOtherLastNmT></MirCliOtherLastNmT>
				<MirCliOtherLastNmT></MirCliOtherLastNmT>
				<MirCliOtherLastNmT></MirCliOtherLastNmT>
				<MirCliOtherLastNmT></MirCliOtherLastNmT>
				<MirCliOtherLastNmT></MirCliOtherLastNmT>
				<MirCliOtherLastNmT></MirCliOtherLastNmT>
				<MirCliOtherLastNmT></MirCliOtherLastNmT>
				<MirCliOtherLastNmT></MirCliOtherLastNmT>
				<MirCliOtherLastNmT></MirCliOtherLastNmT>
				<MirCliOtherLastNmT></MirCliOtherLastNmT>
			</MirCliOtherLastNmG>
		</ApplicationEntryClientSearchData>
		<ReturnCds>
			<MirRetrnCd></MirRetrnCd>
			<LsirReturnCd></LsirReturnCd>
		</ReturnCds>
		<MirUserMsgG>
			<MirUserMsgTxtG>
				<MirUserMsgTxtT></MirUserMsgTxtT>
				<MirUserMsgTxtT></MirUserMsgTxtT>
				<MirUserMsgTxtT></MirUserMsgTxtT>
				<MirUserMsgTxtT></MirUserMsgTxtT>
				<MirUserMsgTxtT></MirUserMsgTxtT>
				<MirUserMsgTxtT></MirUserMsgTxtT>
				<MirUserMsgTxtT></MirUserMsgTxtT>
				<MirUserMsgTxtT></MirUserMsgTxtT>
				<MirUserMsgTxtT></MirUserMsgTxtT>
				<MirUserMsgTxtT></MirUserMsgTxtT>
				<MirUserMsgTxtT></MirUserMsgTxtT>
				<MirUserMsgTxtT></MirUserMsgTxtT>
				<MirUserMsgTxtT></MirUserMsgTxtT>
				<MirUserMsgTxtT></MirUserMsgTxtT>
				<MirUserMsgTxtT></MirUserMsgTxtT>
				<MirUserMsgTxtT></MirUserMsgTxtT>
				<MirUserMsgTxtT></MirUserMsgTxtT>
				<MirUserMsgTxtT></MirUserMsgTxtT>
				<MirUserMsgTxtT></MirUserMsgTxtT>
				<MirUserMsgTxtT></MirUserMsgTxtT>
				<MirUserMsgTxtT></MirUserMsgTxtT>
				<MirUserMsgTxtT></MirUserMsgTxtT>
				<MirUserMsgTxtT></MirUserMsgTxtT>
				<MirUserMsgTxtT></MirUserMsgTxtT>
				<MirUserMsgTxtT></MirUserMsgTxtT>
				<MirUserMsgTxtT></MirUserMsgTxtT>
				<MirUserMsgTxtT></MirUserMsgTxtT>
				<MirUserMsgTxtT></MirUserMsgTxtT>
				<MirUserMsgTxtT></MirUserMsgTxtT>
				<MirUserMsgTxtT></MirUserMsgTxtT>
				<MirUserMsgTxtT></MirUserMsgTxtT>
				<MirUserMsgTxtT></MirUserMsgTxtT>
				<MirUserMsgTxtT></MirUserMsgTxtT>
				<MirUserMsgTxtT></MirUserMsgTxtT>
				<MirUserMsgTxtT></MirUserMsgTxtT>
				<MirUserMsgTxtT></MirUserMsgTxtT>
				<MirUserMsgTxtT></MirUserMsgTxtT>
				<MirUserMsgTxtT></MirUserMsgTxtT>
				<MirUserMsgTxtT></MirUserMsgTxtT>
				<MirUserMsgTxtT></MirUserMsgTxtT>
				<MirUserMsgTxtT></MirUserMsgTxtT>
				<MirUserMsgTxtT></MirUserMsgTxtT>
				<MirUserMsgTxtT></MirUserMsgTxtT>
				<MirUserMsgTxtT></MirUserMsgTxtT>
				<MirUserMsgTxtT></MirUserMsgTxtT>
				<MirUserMsgTxtT></MirUserMsgTxtT>
				<MirUserMsgTxtT></MirUserMsgTxtT>
				<MirUserMsgTxtT></MirUserMsgTxtT>
				<MirUserMsgTxtT></MirUserMsgTxtT>
				<MirUserMsgTxtT></MirUserMsgTxtT>
			</MirUserMsgTxtG>
			<MirUserMsgSevrtyCdG>
				<MirUserMsgSevrtyCdT></MirUserMsgSevrtyCdT>
				<MirUserMsgSevrtyCdT></MirUserMsgSevrtyCdT>
				<MirUserMsgSevrtyCdT></MirUserMsgSevrtyCdT>
				<MirUserMsgSevrtyCdT></MirUserMsgSevrtyCdT>
				<MirUserMsgSevrtyCdT></MirUserMsgSevrtyCdT>
				<MirUserMsgSevrtyCdT></MirUserMsgSevrtyCdT>
				<MirUserMsgSevrtyCdT></MirUserMsgSevrtyCdT>
				<MirUserMsgSevrtyCdT></MirUserMsgSevrtyCdT>
				<MirUserMsgSevrtyCdT></MirUserMsgSevrtyCdT>
				<MirUserMsgSevrtyCdT></MirUserMsgSevrtyCdT>
				<MirUserMsgSevrtyCdT></MirUserMsgSevrtyCdT>
				<MirUserMsgSevrtyCdT></MirUserMsgSevrtyCdT>
				<MirUserMsgSevrtyCdT></MirUserMsgSevrtyCdT>
				<MirUserMsgSevrtyCdT></MirUserMsgSevrtyCdT>
				<MirUserMsgSevrtyCdT></MirUserMsgSevrtyCdT>
				<MirUserMsgSevrtyCdT></MirUserMsgSevrtyCdT>
				<MirUserMsgSevrtyCdT></MirUserMsgSevrtyCdT>
				<MirUserMsgSevrtyCdT></MirUserMsgSevrtyCdT>
				<MirUserMsgSevrtyCdT></MirUserMsgSevrtyCdT>
				<MirUserMsgSevrtyCdT></MirUserMsgSevrtyCdT>
				<MirUserMsgSevrtyCdT></MirUserMsgSevrtyCdT>
				<MirUserMsgSevrtyCdT></MirUserMsgSevrtyCdT>
				<MirUserMsgSevrtyCdT></MirUserMsgSevrtyCdT>
				<MirUserMsgSevrtyCdT></MirUserMsgSevrtyCdT>
				<MirUserMsgSevrtyCdT></MirUserMsgSevrtyCdT>
				<MirUserMsgSevrtyCdT></MirUserMsgSevrtyCdT>
				<MirUserMsgSevrtyCdT></MirUserMsgSevrtyCdT>
				<MirUserMsgSevrtyCdT></MirUserMsgSevrtyCdT>
				<MirUserMsgSevrtyCdT></MirUserMsgSevrtyCdT>
				<MirUserMsgSevrtyCdT></MirUserMsgSevrtyCdT>
				<MirUserMsgSevrtyCdT></MirUserMsgSevrtyCdT>
				<MirUserMsgSevrtyCdT></MirUserMsgSevrtyCdT>
				<MirUserMsgSevrtyCdT></MirUserMsgSevrtyCdT>
				<MirUserMsgSevrtyCdT></MirUserMsgSevrtyCdT>
				<MirUserMsgSevrtyCdT></MirUserMsgSevrtyCdT>
				<MirUserMsgSevrtyCdT></MirUserMsgSevrtyCdT>
				<MirUserMsgSevrtyCdT></MirUserMsgSevrtyCdT>
				<MirUserMsgSevrtyCdT></MirUserMsgSevrtyCdT>
				<MirUserMsgSevrtyCdT></MirUserMsgSevrtyCdT>
				<MirUserMsgSevrtyCdT></MirUserMsgSevrtyCdT>
				<MirUserMsgSevrtyCdT></MirUserMsgSevrtyCdT>
				<MirUserMsgSevrtyCdT></MirUserMsgSevrtyCdT>
				<MirUserMsgSevrtyCdT></MirUserMsgSevrtyCdT>
				<MirUserMsgSevrtyCdT></MirUserMsgSevrtyCdT>
				<MirUserMsgSevrtyCdT></MirUserMsgSevrtyCdT>
				<MirUserMsgSevrtyCdT></MirUserMsgSevrtyCdT>
				<MirUserMsgSevrtyCdT></MirUserMsgSevrtyCdT>
				<MirUserMsgSevrtyCdT></MirUserMsgSevrtyCdT>
				<MirUserMsgSevrtyCdT></MirUserMsgSevrtyCdT>
				<MirUserMsgSevrtyCdT></MirUserMsgSevrtyCdT>
			</MirUserMsgSevrtyCdG>
		</MirUserMsgG>
	</OLifE>
